sagemaker_mlflow/__init__.py
sagemaker_mlflow/auth.py
sagemaker_mlflow/auth_provider.py
sagemaker_mlflow/exceptions.py
sagemaker_mlflow/mlflow_sagemaker_helpers.py
sagemaker_mlflow/mlflow_sagemaker_registry_store.py
sagemaker_mlflow/mlflow_sagemaker_request_header_provider.py
sagemaker_mlflow/mlflow_sagemaker_store.py
sagemaker_mlflow/presigned_url.py
sagemaker_mlflow-0.1.1.dist-info/licenses/LICENSE
sagemaker_mlflow-0.1.1.dist-info/licenses/NOTICE
sagemaker_mlflow-0.1.1.dist-info/METADATA
sagemaker_mlflow-0.1.1.dist-info/WHEEL
sagemaker_mlflow-0.1.1.dist-info/entry_points.txt
sagemaker_mlflow-0.1.1.dist-info/top_level.txt
sagemaker_mlflow-0.1.1.dist-info/RECORD
